PySSPFM/__init__.py
PySSPFM/default_settings.json
PySSPFM/examples_settings.json
PySSPFM/free_1.py
PySSPFM/settings.py
PySSPFM/data_processing/__init__.py
PySSPFM/data_processing/datacube_to_nanoloop_s1.py
PySSPFM/data_processing/datacube_to_nanoloop_s1_params.json
PySSPFM/data_processing/datacube_to_nanoloop_s1_params.toml
PySSPFM/data_processing/nanoloop_to_hyst_s2.py
PySSPFM/data_processing/nanoloop_to_hyst_s2_params.json
PySSPFM/data_processing/nanoloop_to_hyst_s2_params.toml
PySSPFM/gui/__init__.py
PySSPFM/gui/clustering_inertia.py
PySSPFM/gui/curve_clustering.py
PySSPFM/gui/datacube_to_nanoloop_s1.py
PySSPFM/gui/force_curve_clustering.py
PySSPFM/gui/global_map_reader.py
PySSPFM/gui/list_map_reader.py
PySSPFM/gui/loop_file_reader.py
PySSPFM/gui/main.py
PySSPFM/gui/map_correlation.py
PySSPFM/gui/mean_hyst.py
PySSPFM/gui/meas_sheet_generator.py
PySSPFM/gui/nanoloop_to_hyst_s2.py
PySSPFM/gui/phase_inversion_analyzer.py
PySSPFM/gui/phase_offset_analyzer.py
PySSPFM/gui/raw_file_reader.py
PySSPFM/gui/sort_plot_pixel.py
PySSPFM/gui/spm_converter.py
PySSPFM/gui/spm_data_extractor.py
PySSPFM/gui/utils.py
PySSPFM/logo_icon/aip.png
PySSPFM/logo_icon/github.png
PySSPFM/logo_icon/iconPySSPFM.png
PySSPFM/logo_icon/logoPySSPFM.png
PySSPFM/logo_icon/pypi.png
PySSPFM/logo_icon/youtube.png
PySSPFM/logo_icon/zenodo.png
PySSPFM/toolbox/__init__.py
PySSPFM/toolbox/clustering_inertia.py
PySSPFM/toolbox/clustering_inertia_params.json
PySSPFM/toolbox/clustering_inertia_params.toml
PySSPFM/toolbox/curve_clustering.py
PySSPFM/toolbox/curve_clustering_params.json
PySSPFM/toolbox/curve_clustering_params.toml
PySSPFM/toolbox/force_curve_clustering.py
PySSPFM/toolbox/force_curve_clustering_params.json
PySSPFM/toolbox/force_curve_clustering_params.toml
PySSPFM/toolbox/global_map_reader.py
PySSPFM/toolbox/global_map_reader_params.json
PySSPFM/toolbox/global_map_reader_params.toml
PySSPFM/toolbox/list_map_reader.py
PySSPFM/toolbox/list_map_reader_params.json
PySSPFM-2024.12.dist-info/LICENSE.txt
PySSPFM-2024.12.dist-info/METADATA
PySSPFM-2024.12.dist-info/WHEEL
PySSPFM-2024.12.dist-info/entry_points.txt
PySSPFM-2024.12.dist-info/top_level.txt
PySSPFM-2024.12.dist-info/RECORD
