Metadata-Version: 2.2
Name: PySSPFM
Version: 2024.12
Summary: PySSPFM: A specialized tool for Switching Spectroscopy Piezoresponse Force Microscopy (SSPFM) data processing
Home-page: https://github.com/CEA-MetroCarac/PySSPFM
Author: Hugo Valloire, Patrick Quemere
Author-email: "Hugo Valloire, Patrick Quemere" <hugovalloire@gmail.com>
License: GPL v3
Project-URL: Homepage, https://github.com/CEA-MetroCarac/PySSPFM
Project-URL: Documentation, https://github.com/CEA-MetroCarac/PySSPFM/tree/main/doc
Keywords: PySSPFM,SS-PFM,C-KPFM,switching-spectroscopy,PFM,AFM,piezoelectric,ferroelectric,image,hysteresis, nano-loop,piezoresponse,bruker,datacube,spm,python,python-library,data-processing,machine-learning,k-means,cross-correlation
Classifier: Programming Language :: Python :: 3
Classifier: Programming Language :: Python :: 3.7
Classifier: Programming Language :: Python :: 3.8
Classifier: Programming Language :: Python :: 3.9
Classifier: Programming Language :: Python :: 3.10
Classifier: Programming Language :: Python :: 3.11
Classifier: License :: OSI Approved :: GNU General Public License v3 (GPLv3)
Classifier: Operating System :: Microsoft :: Windows
Classifier: Operating System :: POSIX :: Linux
Classifier: Operating System :: MacOS :: MacOS X
Classifier: Environment :: Console
Requires-Python: >=3.7
License-File: LICENSE.txt
Requires-Dist: numpy
Requires-Dist: pandas
Requires-Dist: openpyxl
Requires-Dist: matplotlib
Requires-Dist: Pillow
Requires-Dist: scipy
Requires-Dist: lmfit
Requires-Dist: scikit-learn
Requires-Dist: nanoscope
Requires-Dist: pywin32; platform_system == "Windows"
Dynamic: author
Dynamic: home-page
Dynamic: requires-python
